spektrixpython/__init__.py
spektrixpython/spektrixpython.py
spektrixpython-0.6.1.dist-info/LICENSE
spektrixpython-0.6.1.dist-info/METADATA
spektrixpython-0.6.1.dist-info/WHEEL
spektrixpython-0.6.1.dist-info/RECORD
