Metadata-Version: 2.1
Name: spektrixpython
Version: 0.6.1
Summary: A Python 3 module for interacting with Spektrix API v3. This module is written by a third party and is not supported by or affiliated with Spektrix.
License: MIT
Author: Hugh Topping
Author-email: hugh@crowdengage.com
Requires-Python: >=3.7,<4.0
Classifier: License :: OSI Approved :: MIT License
Classifier: Programming Language :: Python :: 3
Classifier: Programming Language :: Python :: 3.7
Classifier: Programming Language :: Python :: 3.8
Classifier: Programming Language :: Python :: 3.9
Classifier: Programming Language :: Python :: 3.10
Classifier: Programming Language :: Python :: 3.11
Requires-Dist: requests (>=2.31.0,<3.0.0)
